score_rnx/Coranking.py
score_rnx/NXTrusion.py
score_rnx/Pairwisedistances.py
score_rnx/RDMethod.py
score_rnx/ScoreRnx.py
score_rnx/__init__.py
score_rnx/test.py
score_rnx-0.6.dist-info/METADATA
score_rnx-0.6.dist-info/WHEEL
score_rnx-0.6.dist-info/top_level.txt
score_rnx-0.6.dist-info/RECORD
