Metadata-Version: 2.1
Name: score-rnx
Version: 0.6
Summary: Implementacion modular de las métricas Rnx
Home-page: https://github.com/DiegoUrrea195/score_rnx
Author: Carlos David Correa, Diego Ferley Urrea
Author-email: UNKNOWN
License: MIT
Platform: UNKNOWN
Requires-Dist: numpy
Requires-Dist: matplotlib
